read_pi/__init__.py
read_pi/read_pdm.py
read_pi/read_pi.py
read_pi-0.2.7.dist-info/LICENSE
read_pi-0.2.7.dist-info/METADATA
read_pi-0.2.7.dist-info/WHEEL
read_pi-0.2.7.dist-info/top_level.txt
read_pi-0.2.7.dist-info/RECORD
