Metadata-Version: 2.1
Name: read_pi
Version: 0.2.7
Summary: An utility facilitate extracting data from PI Vision and PDM databases.
Author-email: Martin Carlos Araya <maray@equinor.com>
License: MIT License
Project-URL: Homepage, https://github.com/equinor/read_pi
Classifier: License :: OSI Approved :: MIT License
Classifier: Operating System :: OS Independent
Requires-Python: >=3.8
License-File: LICENSE
